Metadata-Version: 2.1
Name: drf-bulk-compat-writable-nested
Version: 0.2.5
Summary: Django REST Framework bulk CRUD view mixins with compatibility for the writable nested serializers package "drf-writable-nested"
Home-page: https://github.com/axmpda/django-rest-framework-bulk/tree/patch-2
Author: Alex Davies & Miroslav Shubernetskiy
Author-email: alex@mooloo.io
License: MIT
Keywords: django
Platform: UNKNOWN
Classifier: Development Status :: 3 - Alpha
Classifier: Framework :: Django
Classifier: Intended Audience :: Developers
Classifier: Operating System :: OS Independent
Classifier: Programming Language :: Python
Classifier: Programming Language :: Python :: 3
Classifier: Topic :: Utilities
Classifier: Topic :: Internet :: WWW/HTTP
Classifier: License :: OSI Approved :: MIT License
Requires-Dist: django
Requires-Dist: djangorestframework
Requires-Dist: setuptools
